LICENSE
MANIFEST.in
README.md
README.rst
pyproject.toml
setup.cfg
setup.py
django_login_auth_app.egg-info/PKG-INFO
django_login_auth_app.egg-info/SOURCES.txt
django_login_auth_app.egg-info/dependency_links.txt
django_login_auth_app.egg-info/requires.txt
django_login_auth_app.egg-info/top_level.txt
login_app/__init__.py
login_app/admin.py
login_app/apps.py
login_app/forms.py
login_app/models.py
login_app/tests.py
login_app/urls.py
login_app/views.py
login_app/migrations/0001_initial.py
login_app/migrations/__init__.py